datahen_helpers/Pandas.py
datahen_helpers/__init__.py
datahen_helpers-0.2.dist-info/LICENSE
datahen_helpers-0.2.dist-info/METADATA
datahen_helpers-0.2.dist-info/WHEEL
datahen_helpers-0.2.dist-info/top_level.txt
datahen_helpers-0.2.dist-info/RECORD
