Metadata-Version: 2.1
Name: datahen-helpers
Version: 0.2
Summary: Datahen package
Home-page: https://datahen.com
Author: Datahen
Author-email: services@datahen.com
License: UNKNOWN
Platform: UNKNOWN
Classifier: Programming Language :: Python :: 3
Classifier: License :: OSI Approved :: MIT License
Classifier: Operating System :: OS Independent
Requires-Python: >=3.6
Requires-Dist: datahen
Requires-Dist: pandas
Requires-Dist: requests
Requires-Dist: tqdm
